MANIFEST.in
requirements.txt
setup.py
test_requirements.txt
versions.txt
cloudshell/__init__.py
cloudshell/octopus/__init__.py
cloudshell/octopus/environment_spec.py
cloudshell/octopus/machine_spec.py
cloudshell/octopus/release_spec.py
cloudshell/octopus/session.py
cloudshell_octopus_deploy.egg-info/PKG-INFO
cloudshell_octopus_deploy.egg-info/SOURCES.txt
cloudshell_octopus_deploy.egg-info/dependency_links.txt
cloudshell_octopus_deploy.egg-info/not-zip-safe
cloudshell_octopus_deploy.egg-info/requires.txt
cloudshell_octopus_deploy.egg-info/top_level.txt