Metadata-Version: 1.0
Name: cloudshell-octopus-deploy
Version: 4.1.93
Summary: Orchestrate Octopus Deploy releases through Cloudshell
Home-page: https://github.com/QualiSystems/cloudshell-octopus-deploy
Author: Nahum Timerman
Author-email: ntimerman@gmail.com
License: Apache Software License 2.0
Keywords: cloudshell quali sandbox cloud octopus deploy
Platform: UNKNOWN
